lib/libtetgen.a
lib/cmake/tetgen/tetgenConfig.cmake
lib/cmake/tetgen/tetgenTargets.cmake
lib/cmake/tetgen/tetgenTargets-release.cmake
lib/cmake/tetgen/tetgenConfigVersion.cmake
lib/cmake/tetgenpy/tetgenpyTargets.cmake
lib/cmake/tetgenpy/tetgenpyTargets-release.cmake
lib/cmake/tetgenpy/tetgenpyConfig.cmake
lib/cmake/tetgenpy/tetgenpyConfigVersion.cmake
tetgenpy/__init__.py
tetgenpy/gentet.py
tetgenpy/plc.py
tetgenpy/tetgenpy_core.cpython-310-x86_64-linux-gnu.so
tetgenpy/_version.py
tetgenpy-0.1.0.dist-info/WHEEL
tetgenpy-0.1.0.dist-info/entry_points.txt
tetgenpy-0.1.0.dist-info/METADATA
tetgenpy-0.1.0.dist-info/RECORD
tetgenpy-0.1.0.dist-info/licenses/LICENSE
include/tetgen.h
include/tetgenpy/py_tetgenio.hpp
include/tetgenpy/print.hpp
include/tetgenpy/py_tetrahedralize.hpp
