Metadata-Version: 2.1
Name: tetgenpy
Version: 0.1.0
Summary: tetgen python wrapper for points, PLCs and tetmesh inputs
Keywords: tetgen,mesh,3D,PLC
Author-Email: Jaewook Lee <jaewooklee042@gmail.com>
License:                     GNU AFFERO GENERAL PUBLIC LICENSE
Classifier: Development Status :: 4 - Beta
Classifier: License :: OSI Approved :: MIT License
Classifier: Programming Language :: Python
Classifier: Programming Language :: Python :: 3.9
Classifier: Programming Language :: Python :: 3.10
Classifier: Programming Language :: Python :: 3.11
Classifier: Programming Language :: Python :: 3.12
Classifier: Programming Language :: Python :: 3.13
Classifier: Natural Language :: English
Classifier: Topic :: Scientific/Engineering
Project-URL: Homepage, https://github.com/tataratat/tetgenpy
Requires-Python: >=3.9
Requires-Dist: numpy
